{
  "lang":"en",
  "name":"pipeline",
  "version":"0.0.0",
  "spacy_version":">=3.2.3,<3.3.0",
  "description":"",
  "author":"",
  "email":"",
  "url":"",
  "license":"",
  "spacy_git_version":"99425de36",
  "vectors":{
    "width":0,
    "vectors":0,
    "keys":0,
    "name":null,
    "mode":"default"
  },
  "labels":{
    "tok2vec":[

    ],
    "ner":[
      "ACCNUM",
      "DATE",
      "LOC",
      "PERSON",
      "PRICE",
      "QTY",
      "STOCKCODE"
    ]
  },
  "pipeline":[
    "tok2vec",
    "ner"
  ],
  "components":[
    "tok2vec",
    "ner"
  ],
  "disabled":[

  ],
  "performance":{
    "ents_f":0.6923076923,
    "ents_p":0.6,
    "ents_r":0.8181818182,
    "ents_per_type":{
      "LOC":{
        "p":0.3333333333,
        "r":1.0,
        "f":0.5
      },
      "PERSON":{
        "p":1.0,
        "r":1.0,
        "f":1.0
      },
      "DATE":{
        "p":1.0,
        "r":1.0,
        "f":1.0
      },
      "ACCNUM":{
        "p":1.0,
        "r":1.0,
        "f":1.0
      },
      "STOCKCODE":{
        "p":0.3333333333,
        "r":0.3333333333,
        "f":0.3333333333
      },
      "PRICE":{
        "p":0.3333333333,
        "r":1.0,
        "f":0.5
      },
      "QTY":{
        "p":1.0,
        "r":1.0,
        "f":1.0
      }
    },
    "tok2vec_loss":0.1842009191,
    "ner_loss":15.497416519
  }
}